datatables/__about__.py
datatables/__init__.py
datatables/admin.py
datatables/apps.py
datatables/datatable.py
datatables/datatable_filters.py
datatables/models.py
datatables/tests.py
datatables/utils.py
datatables/views.py
datatables/migrations/__init__.py
datatables/static/datatables/css/bootstrap.min.css
datatables/static/datatables/css/dataTables.dateTime.min.css
datatables/static/datatables/css/datatables.min.css
datatables/static/datatables/css/select.datatables.min.css
datatables/static/datatables/js/bootstrap.min.js
datatables/static/datatables/js/dataTables.dateTime.min.js
datatables/static/datatables/js/datatables.min.js
datatables/static/datatables/js/datatables.select.min.js
datatables/static/datatables/js/django-datatables.js
datatables/static/datatables/js/jquery-3.6.0.min.js
datatables/static/datatables/js/moment.min.js
datatables/static/datatables/js/popper.min.js
datatables/templates/datatables/_datatable.html
datatables/templates/datatables/base.html
datatables/templates/datatables/css.html
datatables/templates/datatables/datatable.html
datatables/templates/datatables/export.html
datatables/templates/datatables/filters.html
datatables/templates/datatables/js.html
datatables/templates/datatables/table.html
datatables/templates/datatables/toggle-columns.html
datatables/templatetags/__init__.py
datatables/templatetags/datatables.py
django_datatablesview-0.10.1.dist-info/METADATA
django_datatablesview-0.10.1.dist-info/WHEEL
django_datatablesview-0.10.1.dist-info/licenses/LICENSE
django_datatablesview-0.10.1.dist-info/RECORD
