Metadata-Version: 2.4
Name: django-datatablesview
Version: 0.10.1
Summary: A Django app that integrates with DataTables.net javascript api.
Project-URL: Homepage, https://github.com/dahlkar/django-datatables
Author-email: Dahlkar <johan.dahlkar@gmail.com>
License-File: LICENSE
Classifier: Programming Language :: Python
Classifier: Programming Language :: Python :: 3
Classifier: Programming Language :: Python :: 3.8
Classifier: Programming Language :: Python :: 3.9
Classifier: Programming Language :: Python :: 3.10
Classifier: Programming Language :: Python :: 3.11
Requires-Python: >=3.6
Requires-Dist: django>=2.1
